{
	"name": "CopyMOH_CDR_Direct",
	"properties": {
		"activities": [
			{
				"name": "Copy_3xt",
				"type": "Copy",
				"dependsOn": [],
				"policy": {
					"timeout": "7.00:00:00",
					"retry": 0,
					"retryIntervalInSeconds": 30,
					"secureOutput": false,
					"secureInput": false
				},
				"userProperties": [
					{
						"name": "Source",
						"value": "/20200420.csv"
					},
					{
						"name": "Destination",
						"value": "dbo.moh_cdr"
					}
				],
				"typeProperties": {
					"source": {
						"type": "DelimitedTextSource",
						"storeSettings": {
							"type": "FileServerReadSettings",
							"recursive": true
						},
						"formatSettings": {
							"type": "DelimitedTextReadSettings",
							"skipLineCount": 0
						}
					},
					"sink": {
						"type": "SqlDWSink"
					},
					"enableStaging": false,
					"translator": {
						"type": "TabularTranslator",
						"mappings": [
							{
								"source": {
									"type": "DateTimeOffset",
									"ordinal": 1
								},
								"sink": {
									"name": "dateTimeOrigination",
									"type": "DateTimeOffset"
								}
							},
							{
								"source": {
									"type": "String",
									"ordinal": 2
								},
								"sink": {
									"name": "callingPartyNumber",
									"type": "String"
								}
							},
							{
								"source": {
									"type": "String",
									"ordinal": 3
								},
								"sink": {
									"name": "calledPartyNumber",
									"type": "String"
								}
							},
							{
								"source": {
									"type": "Int32",
									"ordinal": 4
								},
								"sink": {
									"name": "callDuration",
									"type": "Int32"
								}
							}
						]
					}
				},
				"inputs": [
					{
						"referenceName": "SourceDataset_3xt",
						"type": "DatasetReference"
					}
				],
				"outputs": [
					{
						"referenceName": "DestinationDataset_3xt",
						"type": "DatasetReference"
					}
				]
			}
		],
		"annotations": []
	},
	"type": "Microsoft.DataFactory/factories/pipelines"
}